{
  "imdb_id": "tt2825924",
  "tmdb_id": "220468",
  "douban_id": null,
  "title": "Revelation Road 2: The Sea of Glass and Fire (2013)",
  "genres": [
    "Action",
    "Fantasy"
  ],
  "country": "USA",
  "version": [
    {
      "runtime": "90 min",
      "description": ""
    }
  ],
  "imdb_rating": 5.3,
  "director": [
    {
      "id": "nm0754817",
      "name": "Gabriel Sabloff"
    }
  ],
  "writer": [
    {
      "id": "nm0614701",
      "name": "Sean Paul Murphy",
      "description": null
    },
    {
      "id": "nm0754817",
      "name": "Gabriel Sabloff",
      "description": null
    }
  ],
  "cast": [
    {
      "id": "nm0924684",
      "name": "David A.R. White",
      "character": "Josh"
    },
    {
      "id": "nm0098372",
      "name": "Brian Bosworth",
      "character": "Hawg"
    },
    {
      "id": "nm0000616",
      "name": "Eric Roberts",
      "character": "Sheriff Jensen"
    },
    {
      "id": "nm1689139",
      "name": "Andrea Logan White",
      "character": "Cat"
    },
    {
      "id": "nm2366492",
      "name": "Noell Coet",
      "character": "Beth"
    },
    {
      "id": "nm0096165",
      "name": "Steve Borden",
      "character": "Junkyard"
    },
    {
      "id": "nm0545622",
      "name": "Bruce Marchiano",
      "character": "The Stranger"
    },
    {
      "id": "nm1651426",
      "name": "Morgan Leslie",
      "character": "Gail"
    },
    {
      "id": "nm0022323",
      "name": "Ryan Alosio",
      "character": "John Dean Carver"
    },
    {
      "id": "nm1918574",
      "name": "Leticia Robles",
      "character": "Claudia"
    },
    {
      "id": "nm2373595",
      "name": "Jen Lilley",
      "character": "Rachel"
    },
    {
      "id": "nm0936403",
      "name": "Ray Wise",
      "character": "Frank"
    },
    {
      "id": "nm0060302",
      "name": "Roberta Bassin",
      "character": "Kathy Jenson"
    },
    {
      "id": "nm0512402",
      "name": "Tracy Melchior",
      "character": "Lynette"
    },
    {
      "id": "nm3928510",
      "name": "Madison Gibney",
      "character": "Maureen"
    },
    {
      "id": "nm5288601",
      "name": "Maverick Von Haug",
      "character": "Meat"
    },
    {
      "id": "nm5091078",
      "name": "Mavrick Von Haug",
      "character": "Meat"
    },
    {
      "id": "nm0410336",
      "name": "Mark Irvingsen",
      "character": "Irving"
    },
    {
      "id": "nm0674194",
      "name": "Monte Rex Perlin",
      "character": "Griz /              Taliban Soldier"
    },
    {
      "id": "nm4545528",
      "name": "Ron Kari",
      "character": "Crab"
    },
    {
      "id": "nm1575945",
      "name": "Laksh Singh",
      "character": "Dinesh"
    },
    {
      "id": "nm1594757",
      "name": "Russell Wolfe",
      "character": "Lt. Parsons"
    },
    {
      "id": "nm0778931",
      "name": "Carey Scott",
      "character": "Deputy Cooper"
    },
    {
      "id": "nm2057822",
      "name": "Dave Vescio",
      "character": "Dale"
    },
    {
      "id": "nm0685116",
      "name": "David Pires",
      "character": "Todd"
    },
    {
      "id": "nm0899604",
      "name": "Dea Vise",
      "character": "Tammy"
    },
    {
      "id": "nm0135589",
      "name": "Jordana Capra",
      "character": "Dr. Cynthia Sloan"
    },
    {
      "id": "nm4687538",
      "name": "Kevin Hoffmann",
      "character": "Scientist"
    },
    {
      "id": "nm3500674",
      "name": "Michael John Lane",
      "character": "Crazy Jack"
    },
    {
      "id": "nm0584151",
      "name": "Joseph Lee Michael",
      "character": "Mearle /              General"
    },
    {
      "id": "nm0381680",
      "name": "Kyle Hester",
      "character": "Captive Biker"
    },
    {
      "id": "nm3596982",
      "name": "Leon Walker",
      "character": "D-Block"
    },
    {
      "id": "nm2612993",
      "name": "Dave Marlin",
      "character": "Murzad"
    },
    {
      "id": "nm5627001",
      "name": "Erik Carapert",
      "character": "Taliban Soldier"
    },
    {
      "id": "nm2141926",
      "name": "William De Vital",
      "character": "Taliban Soldier       (as William Devital)"
    },
    {
      "id": "nm0044122",
      "name": "Koby Azarly",
      "character": "Taliban Soldier"
    },
    {
      "id": "nm0175510",
      "name": "Kass Connors",
      "character": "Taliban Soldier"
    },
    {
      "id": "nm0436064",
      "name": "David Kallaway",
      "character": "Taliban Soldier       (as David Kaplan Kallaway)"
    },
    {
      "id": "nm0289716",
      "name": "David 'Shark' Fralick",
      "character": "Onionhead"
    },
    {
      "id": "nm0492764",
      "name": "Frederick Lawrence",
      "character": "Zeb"
    },
    {
      "id": "nm0574465",
      "name": "Lorin McCraley",
      "character": "Frog"
    },
    {
      "id": "nm0267760",
      "name": "Jerry Farmer",
      "character": "Scab"
    },
    {
      "id": "nm7879010",
      "name": "James Fernandez",
      "character": "Doc       (as James 'Chico' Fernandez)"
    },
    {
      "id": "nm0731067",
      "name": "Eliza Roberts",
      "character": "Marion"
    },
    {
      "id": "nm0317364",
      "name": "Michael Gier",
      "character": "Bill"
    },
    {
      "id": "nm2761362",
      "name": "Sean Gibney",
      "character": "Donnie"
    },
    {
      "id": "nm7879011",
      "name": "Frankie Brumm",
      "character": "Tracy"
    },
    {
      "id": "nm7879012",
      "name": "Ben Scott",
      "character": "Federal Agent"
    },
    {
      "id": "nm4308736",
      "name": "Ocean White",
      "character": "Baby Natalie"
    },
    {
      "id": "nm4437653",
      "name": "Ciddy Fonteboa",
      "character": "Bianca"
    },
    {
      "id": "nm5336240",
      "name": "Ed Hernandez",
      "character": "Mechanic"
    },
    {
      "id": "nm7879013",
      "name": "Maura Murphy",
      "character": "Biker Girl"
    },
    {
      "id": "nm1717682",
      "name": "Sarah Prikryl",
      "character": "Narrator       (voice)"
    }
  ],
  "overview": "ROAD 2: THE SEA OF GLASS AND FIRE picks up where the first film in the series ends. After the rapture has taken place, JOSH MCMANUS (David A. R. White) is left behind and goes on a journey to find out what has happened and attempts to travel home to find his family. Before he can go anywhere, he is confronted again by the biker gang that harassed him previously and he joins forces with a young girl whose family has been taken up into the sky by God along with other believers. Chasing Josh at every turn is the brutal outlaw HAWG (Brian Bosworth) and his rolling gang of killers. On the day after the Biblical rapture, law and order have broken down - the highways have become a no-mans-land of bandits and looters. Josh's world has been shaken to the core, and he must make a choice, embrace his past as a man of violence, or learn a new path and become a man of faith. Which will he choose?",
  "storyline": "Revelation Road 2: The Sea of Glass and Fire continues the thrilling odyssey of Josh McManus, as he struggles to return home to his wife and daughter. Helping Josh on his epic quest is a local Sheriff, the over-eager sidekick Beth, and the renegade biker Cat. Chasing Josh at every turn is brutal outlaw Hawg and his loyal gang of homicidal bikers.",
  "plot": null,
  "synopsis": "ROAD 2: THE SEA OF GLASS AND FIRE picks up where the first film in the series ends. After the rapture has taken place, JOSH MCMANUS (David A. R. White) is left behind and goes on a journey to find out what has happened and attempts to travel home to find his family. Before he can go anywhere, he is confronted again by the biker gang that harassed him previously and he joins forces with a young girl whose family has been taken up into the sky by God along with other believers. Chasing Josh at every turn is the brutal outlaw HAWG (Brian Bosworth) and his rolling gang of killers. On the day after the Biblical rapture, law and order have broken down - the highways have become a no-mans-land of bandits and looters. Josh's world has been shaken to the core, and he must make a choice, embrace his past as a man of violence, or learn a new path and become a man of faith. Which will he choose?Helping Josh on his epic quest is the local Sheriff (ERIC ROBERTS), Beth, his over-eager sidekick (NOELL COET) and Cat, the renegade biker (ANDREA LOGAN WHITE). Also featuring WCW Star STEVE \"STING\" BORDAN and BRUCE MARCHIANO as The Stranger."
}