{
  "imdb_id": "tt3283718",
  "tmdb_id": "255156",
  "douban_id": null,
  "title": "H\u00fck\u00fcmet Kadin 2 (2013)",
  "genres": [
    "Comedy"
  ],
  "country": "Turkey",
  "version": [
    {
      "runtime": "105 min",
      "description": ""
    }
  ],
  "imdb_rating": 6.0,
  "director": [
    {
      "id": "nm1195585",
      "name": "Sermiyan Midyat"
    }
  ],
  "writer": [
    {
      "id": "nm1195585",
      "name": "Sermiyan Midyat",
      "description": null
    }
  ],
  "cast": [
    {
      "id": "nm0015130",
      "name": "Demet Akbag",
      "character": "Xate"
    },
    {
      "id": "nm1941926",
      "name": "Ercan Kesal",
      "character": "Aziz Veysel"
    },
    {
      "id": "nm1195585",
      "name": "Sermiyan Midyat",
      "character": "Faruk"
    },
    {
      "id": "nm2240777",
      "name": "Osman Alkas",
      "character": "Veysi"
    },
    {
      "id": "nm1055039",
      "name": "Ayberk Atilla",
      "character": "Seyhmuz"
    },
    {
      "id": "nm2457274",
      "name": "Sarp Aydinoglu",
      "character": "Teacher Peyami"
    },
    {
      "id": "nm7065123",
      "name": "Irfan Aydogan",
      "character": "Bilal"
    },
    {
      "id": "nm7067814",
      "name": "Hamir Demir",
      "character": "Cinci Hoca"
    },
    {
      "id": "nm7067821",
      "name": "Necmiye Demir",
      "character": "Berfo"
    },
    {
      "id": "nm2899097",
      "name": "Bahadir Efe",
      "character": "Bedri"
    },
    {
      "id": "nm5480435",
      "name": "Ipek Elban",
      "character": "Nevide"
    },
    {
      "id": "nm7065119",
      "name": "Faruk Enterli",
      "character": "Firat"
    },
    {
      "id": "nm4311816",
      "name": "Elif Erdogan",
      "character": "Rukiye"
    },
    {
      "id": "nm7065118",
      "name": "Hakan Erkuran",
      "character": "Numan"
    },
    {
      "id": "nm7067815",
      "name": "G\u00fcrsel Firat",
      "character": "Nazmi"
    },
    {
      "id": "nm3532880",
      "name": "Burcu G\u00f6nder",
      "character": "Gule"
    },
    {
      "id": "nm7067816",
      "name": "\u00d6zg\u00fcr G\u00f6nenler",
      "character": "Postman (Postaci)"
    },
    {
      "id": "nm7067817",
      "name": "G\u00fcven\u00e7 G\u00fcm\u00fcs",
      "character": "Jak"
    },
    {
      "id": "nm5479779",
      "name": "Levent Idem",
      "character": "Nedim"
    },
    {
      "id": "nm1759076",
      "name": "Mahir Ipek",
      "character": "Ikram"
    },
    {
      "id": "nm7065122",
      "name": "Mehmet Ka\u00e7iran",
      "character": "Isa"
    },
    {
      "id": "nm0969460",
      "name": "Hayk Kirakosyan",
      "character": "Photographer"
    },
    {
      "id": "nm0702676",
      "name": "Nazmi Kirik",
      "character": "Ferhat"
    },
    {
      "id": "nm7067715",
      "name": "Hazim Kisak\u00fcrek",
      "character": "Fehime's Grandfather"
    },
    {
      "id": "nm7067818",
      "name": "Azad Mese",
      "character": "Tatlici"
    },
    {
      "id": "nm7067819",
      "name": "Kadir Parlak",
      "character": "Commander"
    },
    {
      "id": "nm3105058",
      "name": "Dogukan Polat",
      "character": "S\u00fcleyman"
    },
    {
      "id": "nm7067714",
      "name": "Ferit Saglam",
      "character": "Faruk's Grandfather"
    },
    {
      "id": "nm3957705",
      "name": "Ahmet Sarsilmaz",
      "character": "Yusuf"
    },
    {
      "id": "nm7067820",
      "name": "Mustafa Hilmi Sipahi",
      "character": "Imam"
    },
    {
      "id": "nm1855469",
      "name": "Mine Teber",
      "character": "Sidar"
    },
    {
      "id": "nm3252911",
      "name": "G\u00fclhan Tekin",
      "character": "Fehime       (as Gulhan Tekin)"
    },
    {
      "id": "nm7065124",
      "name": "S\u00fcmer Tekin",
      "character": "Mahmudo"
    },
    {
      "id": "nm4820957",
      "name": "Olgun Toker",
      "character": "Adnan"
    },
    {
      "id": "nm3082795",
      "name": "Arda Turan",
      "character": ""
    },
    {
      "id": "nm1197528",
      "name": "Mustafa Turan",
      "character": "Merdan"
    },
    {
      "id": "nm6432844",
      "name": "Mehmet Yasiru",
      "character": "Abdurrahim Dede"
    },
    {
      "id": "nm3635683",
      "name": "Dilek Yorulmaz",
      "character": "Z\u00fcmre"
    },
    {
      "id": "nm6445429",
      "name": "Zafer \u00c7ika",
      "character": "New Governor"
    },
    {
      "id": "nm2053211",
      "name": "B\u00fclent \u00c7olak",
      "character": "Baran"
    },
    {
      "id": "nm6445390",
      "name": "Seher \u00c7uhadar",
      "character": "Ebe Hatice       (as Seher Cuhadar)"
    }
  ],
  "overview": null,
  "storyline": "Hukumet Kadin 2 is the second installment of the series. The second film goes back to the year 1949 and follows the journey of the main character Xate and her sons and daughter as she campaigns on behalf of her recently jailed husband. Xate's nemesis Faruk rallies against her, trying to win the elections himself. Xate works hard both to win the elections and to make sure her village gets to have a brand new school. Just like in the first film, the entire shooting took place in Midyat.",
  "plot": null,
  "synopsis": null
}