{
  "imdb_id": "tt3613084",
  "tmdb_id": "287399",
  "douban_id": null,
  "title": "Supermen: A Story of British Wrestlers (2014)",
  "genres": [
    "Documentary",
    "Sport"
  ],
  "country": "UK",
  "version": [
    {
      "runtime": "54 min",
      "description": ""
    }
  ],
  "imdb_rating": 7.0,
  "director": [
    {
      "id": "nm4103866",
      "name": "Hassan Otsmane-Elhaou"
    }
  ],
  "writer": [
    {
      "id": "nm4103866",
      "name": "Hassan Otsmane-Elhaou",
      "description": "story"
    },
    {
      "id": "nm4103866",
      "name": "Hassan Otsmane-Elhaou",
      "description": null
    }
  ],
  "cast": null,
  "overview": "Supermen: A Story of British Wrestlers is a feature-length documentary film focused on what it's like to live a life in wrestling.",
  "storyline": "Supermen: A Story of British Wrestlers is a documentary film that explores what a life in British wrestling is like. In the film, wrestlers with ages ranging from 17 to over 60 discuss their involvement in wrestling, and how it has changed and shaped their lives. The film inter-cuts between wrestlers of differing ages, experience and backgrounds to create a dialogue and give a full picture of the whole experience. Topics covered include injuries, sacrifices, family and relationships, the dream of going to America and more.",
  "plot": null,
  "synopsis": null
}