{
  "imdb_id": "tt4066748",
  "tmdb_id": "303285",
  "douban_id": null,
  "title": "R.E.M. by MTV (2014)",
  "genres": [
    "Documentary"
  ],
  "country": "USA",
  "version": [
    {
      "runtime": "107 min",
      "description": ""
    }
  ],
  "imdb_rating": 7.3,
  "director": [
    {
      "id": "nm1844315",
      "name": "Alex Young"
    }
  ],
  "writer": [
    {
      "id": "nm1810380",
      "name": "David Leopold",
      "description": null
    },
    {
      "id": "nm1844315",
      "name": "Alex Young",
      "description": null
    }
  ],
  "cast": [
    {
      "id": "nm0077494",
      "name": "Bill Berry",
      "character": "Himself"
    },
    {
      "id": "nm0090358",
      "name": "Jay Boberg",
      "character": "Himself"
    },
    {
      "id": "nm0118407",
      "name": "Peter Buck",
      "character": "Himself"
    },
    {
      "id": "nm0170306",
      "name": "Stephen Colbert",
      "character": "Himself"
    },
    {
      "id": "nm1685643",
      "name": "Neil Cole",
      "character": "MTV Host"
    },
    {
      "id": "nm0178608",
      "name": "Ian Copeland",
      "character": "Himself"
    },
    {
      "id": "nm1290184",
      "name": "Don Dixon",
      "character": "Himself"
    },
    {
      "id": "nm2357020",
      "name": "Mitch Easter",
      "character": "Himself"
    },
    {
      "id": "nm1961992",
      "name": "Don Gehman",
      "character": "Himself"
    },
    {
      "id": "nm6905507",
      "name": "John Keane",
      "character": "Himself"
    },
    {
      "id": "nm0517064",
      "name": "Kurt Loder",
      "character": "Himself"
    },
    {
      "id": "nm0001482",
      "name": "Courtney Love",
      "character": "Herself"
    },
    {
      "id": "nm6905506",
      "name": "Pat McCarthy",
      "character": "Himself"
    },
    {
      "id": "nm0590121",
      "name": "Mike Mills",
      "character": "Himself"
    },
    {
      "id": "nm0695470",
      "name": "Jane Pratt",
      "character": "Herself"
    },
    {
      "id": "nm0814832",
      "name": "Tabitha Soren",
      "character": "Herself"
    },
    {
      "id": "nm0829537",
      "name": "Jon Stewart",
      "character": "Himself"
    },
    {
      "id": "nm0005468",
      "name": "Michael Stipe",
      "character": "Himself"
    },
    {
      "id": "nm0891641",
      "name": "Eddie Vedder",
      "character": "Himself"
    },
    {
      "id": "nm0953439",
      "name": "Peter Zaremba",
      "character": "Himself"
    }
  ],
  "overview": "The career of the band, from its start in Georgia to its breakup in 2011.",
  "storyline": "On April 5, 1980 four college pals-Bill Berry, Peter Buck, Mike Mills and Michael Stipe-took the stage together for the first time to play at a friend's birthday party. The band they started that night stayed together for thirty years and changed the shape of rock music. R.E.M. By MTV tells R.E.M.'s story in their own words, through three decades of performances and interviews R.E.M gave to MTV channels in the USA and around the world. Featuring revealing, never-before-seen footage, R.E.M. By MTV tells the amazing story of a band that did it their own way, and changed how a generation of musicians after them did it, too.",
  "plot": null,
  "synopsis": null
}