{
  "imdb_id": "tt5539186",
  "tmdb_id": "396692",
  "douban_id": null,
  "title": "Amityville: Vanishing Point (2016)",
  "genres": [
    "Horror"
  ],
  "country": "USA",
  "version": [
    {
      "runtime": "92 min",
      "description": ""
    }
  ],
  "imdb_rating": 3.1,
  "director": [
    {
      "id": "nm6663772",
      "name": "Dylan Greenberg"
    }
  ],
  "writer": [
    {
      "id": "nm7631895",
      "name": "Pailer Ezra",
      "description": "co-writer"
    },
    {
      "id": "nm6663772",
      "name": "Dylan Greenberg",
      "description": "story"
    },
    {
      "id": "nm3787315",
      "name": "Selena Mars",
      "description": "co-writer"
    },
    {
      "id": "nm7988982",
      "name": "Jurgen Azazel Munster",
      "description": "co-writer"
    }
  ],
  "cast": [
    {
      "id": "nm3787315",
      "name": "Selena Mars",
      "character": "Ms. Aphrodite Ernie"
    },
    {
      "id": "nm6925146",
      "name": "Amanda Flowers",
      "character": "Brigitta Lynn"
    },
    {
      "id": "nm6663775",
      "name": "Mickala McFarlane",
      "character": "Bermuda Ernie"
    },
    {
      "id": "nm7988982",
      "name": "Jurgen Azazel Munster",
      "character": "Hank Denton"
    },
    {
      "id": "nm7500171",
      "name": "Sara Kaiser",
      "character": "Sentinel Ernie"
    },
    {
      "id": "nm6925139",
      "name": "Max Husten",
      "character": "Jack Rockwell, Wayward Boy"
    },
    {
      "id": "nm3479339",
      "name": "Victor M. Sheely",
      "character": "Father Mars"
    },
    {
      "id": "nm7230263",
      "name": "Alyssa Marie C.",
      "character": "Moth Abacus"
    },
    {
      "id": "nm7988983",
      "name": "Rose Kaplan",
      "character": "Maude Abacus"
    },
    {
      "id": "nm6227090",
      "name": "Jesse Yungbei",
      "character": "The Demon"
    },
    {
      "id": "nm7988984",
      "name": "David Marquise",
      "character": "Antonia Abacus"
    },
    {
      "id": "nm7988985",
      "name": "Taylor MacLeod",
      "character": "Ricki Flynt"
    },
    {
      "id": "nm7988986",
      "name": "Alexia Giovanna",
      "character": "Joan Flynt"
    },
    {
      "id": "nm7631867",
      "name": "Neva Gentlman",
      "character": "Neva, the Bellydancer"
    },
    {
      "id": "nm7631862",
      "name": "Lucy Love",
      "character": "Sodia"
    },
    {
      "id": "nm5709574",
      "name": "Louisa Ashleigh",
      "character": "Glass Sky       (as Louisa Ashleigh Krupp)"
    },
    {
      "id": "nm6925149",
      "name": "Carl Peckham",
      "character": "Sardu the Gravedigger"
    },
    {
      "id": "nm7988987",
      "name": "Lys Obsidian",
      "character": "Lys Obsidian Absurd the Magnificent Sword Dancer"
    },
    {
      "id": "nm5696920",
      "name": "Piera Yerkes",
      "character": "Stephanie Garlic"
    },
    {
      "id": "nm7988988",
      "name": "Liz Grayson",
      "character": "Errol Stone"
    },
    {
      "id": "nm7988989",
      "name": "Peter Russell",
      "character": "Silent Pete"
    },
    {
      "id": "nm6925148",
      "name": "Aaden Grushkin",
      "character": "Altair, the Bassist"
    },
    {
      "id": "nm7631876",
      "name": "Dan Correll",
      "character": "Ranston Cubicle"
    },
    {
      "id": "nm7988990",
      "name": "Max Gnar",
      "character": "Max Gnar"
    },
    {
      "id": "nm2674743",
      "name": "John Patrick Brennan",
      "character": "Bacon Cheeseburger       (as John P. Brennan)"
    },
    {
      "id": "nm7988991",
      "name": "Julia Simonello",
      "character": "Ace of Spades Woman"
    },
    {
      "id": "nm7988993",
      "name": "Emily Smykal",
      "character": "Dancer in the Dark"
    },
    {
      "id": "nm0442207",
      "name": "Lloyd Kaufman",
      "character": "Elron Randall, an Intellectual"
    },
    {
      "id": "nm3313554",
      "name": "Catherine Corcoran",
      "character": "Cara"
    },
    {
      "id": "nm3575770",
      "name": "Zac Amico",
      "character": "Vaggio"
    },
    {
      "id": "nm5338289",
      "name": "Neon Music",
      "character": "Neon Music"
    },
    {
      "id": "nm6615946",
      "name": "Dean Dempsey",
      "character": "Himself"
    },
    {
      "id": "nm7035262",
      "name": "Lucille Bignom",
      "character": "Herself"
    },
    {
      "id": "nm5406313",
      "name": "Rew Starr",
      "character": "Herself"
    },
    {
      "id": "nm7988992",
      "name": "Lindsay Lowe",
      "character": "Concetta"
    },
    {
      "id": "nm7631858",
      "name": "Sofe Cote",
      "character": "Margaret East"
    }
  ],
  "overview": "The Amityville legend lives on when a resident of a local boarding house dies under mysterious circumstances. Her two best friends, Brigitta and Bermuda, Bermuda's sister Sentinel, and the owner of the boarding house, Ms. Ernie, are absolutely devastated. This is not helped by the arrival of an eccentric and crude detective who never takes off his cowboy outfit, Hank Denton. Tensions run high as the girls begin to suspect their friend Margaret may still be alive; and as the detective's behavior becomes more out of control, the house itself may very well be turning on it's residents.",
  "storyline": "The Amityville legend lives on when a resident of a local boarding house dies under mysterious circumstances. Her two best friends, Brigitta and Bermuda, Bermuda's sister Sentinel, and the owner of the boarding house, Ms. Ernie, are absolutely devastated. This is not helped by the arrival of an eccentric and crude detective who never takes off his cowboy outfit, Hank Denton. Tensions run high as the girls begin to suspect their friend Margaret may still be alive; and as the detective's behavior becomes more out of control, the house itself may very well be turning on it's residents.",
  "plot": null,
  "synopsis": null
}