{
  "imdb_id": "tt6012754",
  "tmdb_id": "414969",
  "douban_id": null,
  "title": "Owls & Mice (2016)",
  "genres": [
    "Drama",
    "Family",
    "Musical"
  ],
  "country": "Netherlands",
  "version": [
    {
      "runtime": "80 min",
      "description": ""
    }
  ],
  "imdb_rating": 6.2,
  "director": [
    {
      "id": "nm0244697",
      "name": "Simone van Dusseldorp"
    }
  ],
  "writer": [
    {
      "id": "nm0244697",
      "name": "Simone van Dusseldorp",
      "description": null
    }
  ],
  "cast": [
    {
      "id": "nm8397368",
      "name": "Hiba Ghafry",
      "character": "Meral"
    },
    {
      "id": "nm4272106",
      "name": "Mariana Aparicio Torres",
      "character": "Serine"
    },
    {
      "id": "nm0643124",
      "name": "Mimoun Oa\u00efssa",
      "character": "Aziz"
    },
    {
      "id": "nm0287564",
      "name": "Bob Fosko",
      "character": "Verhuizer"
    },
    {
      "id": "nm6707808",
      "name": "Matheu Hinzen",
      "character": "Jason"
    },
    {
      "id": "nm7183142",
      "name": "Felix van de Weerdt",
      "character": "Vito"
    },
    {
      "id": "nm8555507",
      "name": "Jashayra Oehlers",
      "character": "Desi"
    },
    {
      "id": "nm8397369",
      "name": "Sharai Troostwijk",
      "character": "Sharai Klittenband"
    },
    {
      "id": "nm8397370",
      "name": "Alexander Silva Verstappen Grin",
      "character": "Alexander Klittenband"
    },
    {
      "id": "nm8314557",
      "name": "Hayo De Wilde",
      "character": "Hayo Klittenband"
    },
    {
      "id": "nm8397371",
      "name": "Tyrone Sjauw Pan",
      "character": "Tyrone Klittenband"
    },
    {
      "id": "nm8397372",
      "name": "Bente Wallenburg",
      "character": "Bente Klittenband"
    },
    {
      "id": "nm8808426",
      "name": "Jade de Bruin",
      "character": "Jade Klittenband"
    },
    {
      "id": "nm8808427",
      "name": "Tamar van Zutphen",
      "character": "Tamar Klittenband"
    },
    {
      "id": "nm1455825",
      "name": "Birgit Schuurman",
      "character": "Juf Ietje"
    },
    {
      "id": "nm3100438",
      "name": "Fabian Jansen",
      "character": "Hutpvader"
    },
    {
      "id": "nm3148900",
      "name": "Rosanne Hogewoning",
      "character": "Hutpmoeder 1"
    },
    {
      "id": "nm6571948",
      "name": "Cindy Wijdenbosch",
      "character": "Hutpmoeder 2"
    },
    {
      "id": "nm0388640",
      "name": "Ren\u00e9 van 't Hof",
      "character": "Boswachter"
    },
    {
      "id": "nm8808428",
      "name": "Dirk van der Burg",
      "character": "Klasgenoot"
    },
    {
      "id": "nm8808429",
      "name": "Dr\u00e9 van der Burg",
      "character": "Klasgenoot"
    },
    {
      "id": "nm8808430",
      "name": "Dani Eikelenboom",
      "character": "Klasgenoot"
    },
    {
      "id": "nm8808431",
      "name": "Kaya Hunze",
      "character": "Klasgenoot"
    },
    {
      "id": "nm8500587",
      "name": "Vygo de Klein",
      "character": "Klasgenoot       (as Vygo Brent de Klein)"
    },
    {
      "id": "nm8808432",
      "name": "Chioma Koelman",
      "character": "Klasgenoot"
    },
    {
      "id": "nm8808433",
      "name": "Sophie Petrovic",
      "character": "Klasgenoot"
    },
    {
      "id": "nm8808434",
      "name": "Naomi Saensuk",
      "character": "Klasgenoot"
    },
    {
      "id": "nm5601190",
      "name": "Roosje Somers",
      "character": "Klasgenoot"
    },
    {
      "id": "nm8808435",
      "name": "Imani Sarah Williams",
      "character": "Klasgenoot"
    }
  ],
  "overview": null,
  "storyline": "Meral (8) just moved into a new town. She tries to make friends at her new school before their autumn school camp, but this is harder than expected. At home she befriends a little mouse that lives in her new room, which she calls Peepeep. Afraid that her parents will kill Peepeep while she is away, she secretly takes him with her. Thanks to the mouse, Meral makes some unexpected new friends. When an owl catches the little mouse, Meral blames her new friends. It is not until they set out into the wild to retrieve the owl pellet with Peepeep's bones that Meral finally understands what friendship is all about. OWLS & MICE is the sequel of the successful and award-winning FROGS & TOADS, from the same writer and director Simone van Dusseldorp.",
  "plot": null,
  "synopsis": null
}